gcp_utils_sds/__init__.py
gcp_utils_sds/access_secrets.py
gcp_utils_sds/buckets.py
gcp_utils_sds/yoy.py
gcp_utils_sds-0.2.2.dist-info/licenses/LICENSE
gcp_utils_sds-0.2.2.dist-info/METADATA
gcp_utils_sds-0.2.2.dist-info/WHEEL
gcp_utils_sds-0.2.2.dist-info/top_level.txt
gcp_utils_sds-0.2.2.dist-info/RECORD
