Metadata-Version: 2.4
Name: gcp_utils_sds
Version: 0.2.2
Summary: Utilities functions for interacting with GCP tools
Home-page: 
Author: Sam Taylor
Author-email: 2015samtaylor@gmail.com
Classifier: Programming Language :: Python :: 3
Classifier: License :: OSI Approved :: MIT License
Classifier: Operating System :: OS Independent
Requires-Python: >=3.7
License-File: LICENSE
Requires-Dist: google-cloud-storage
Requires-Dist: google-cloud-secret-manager
Requires-Dist: google-auth
Requires-Dist: google-auth-oauthlib
Requires-Dist: pandas
Requires-Dist: google-cloud-bigquery
Dynamic: author
Dynamic: author-email
Dynamic: classifier
Dynamic: description
Dynamic: description-content-type
Dynamic: license-file
Dynamic: requires-dist
Dynamic: requires-python
Dynamic: summary
